dice/__init__.py
dice/dice.py
dice/dice_simulation.py
dice_tb-0.0.1.dist-info/LICENSE
dice_tb-0.0.1.dist-info/METADATA
dice_tb-0.0.1.dist-info/WHEEL
dice_tb-0.0.1.dist-info/top_level.txt
dice_tb-0.0.1.dist-info/RECORD
