Metadata-Version: 2.1
Name: dice_tb
Version: 0.0.1
Summary: A simple dice package which has a type Dice
Author-email: Thomas Brumbaugh <thomas.william.brumbaugh@gmail.com>
Project-URL: Homepage, https://github.com/dice_tb
Project-URL: Issues, https://github.com/pypa/dice_tb/issues
Classifier: Programming Language :: Python :: 3
Classifier: License :: OSI Approved :: MIT License
Classifier: Operating System :: OS Independent
Requires-Python: >=3.8
License-File: LICENSE
